setup.py
Client/app_clients.py
Client/client_controller.py
Client/datachannel_client.py
Client/ping_client.py
Client/utils.py
Client/yaml_validator.py
Federated_Learning_Client.egg-info/PKG-INFO
Federated_Learning_Client.egg-info/SOURCES.txt
Federated_Learning_Client.egg-info/dependency_links.txt
Federated_Learning_Client.egg-info/top_level.txt